moi_perviy_packet/__init__.py
moi_perviy_packet/common_functions.py
moi_perviy_packet/db_functions.py
moi_perviy_packet-0.1.dist-info/METADATA
moi_perviy_packet-0.1.dist-info/WHEEL
moi_perviy_packet-0.1.dist-info/top_level.txt
moi_perviy_packet-0.1.dist-info/RECORD
