Metadata-Version: 2.1
Name: moi-perviy-packet
Version: 0.1
Summary: this is my first test package
Author: Lev
Author-email: example@ex.amp
